MANIFEST.in
setup.cfg
setup.py
epos/__init__.py
epos.egg-info/PKG-INFO
epos.egg-info/SOURCES.txt
epos.egg-info/dependency_links.txt
epos.egg-info/not-zip-safe
epos.egg-info/top_level.txt