Metadata-Version: 1.0
Name: epos
Version: 0.0.1
Summary: DAG Task scheduler and DSL on top of Mesos
Home-page: http://github.com/kszucs/epos
Author: Krisztian Szucs
Author-email: szucs.krisztian@gmail.com
License: BSD
Keywords: task-scheduling parallelism mesos spark
Platform: UNKNOWN
